Metadata-Version: 2.1
Name: rsi-calculator
Version: 0.1.0
Summary: A library to calculating RSI.
Home-page: https://github.com/onuratakan/rsi_calculator
Author: Onur Atakan ULUSOY
Author-email: atadogan06@gmail.com
License: MIT
Platform: UNKNOWN
Requires-Python: >= 3
License-File: LICENSE
